{
    "title" : "En una ciutat se seguí que hun dispost jove… Diari d’un nòmada sidós (11) Ayahuasca",
    "url" : "diari-d-un-nomada-sidos-11",
    "section" : "creacio",
    "issue" : 31,
    "data" : "27/01/2024",
    "imageCard" : "andreu31-02-01",
    "author" : "Andreu Pérez-Mingorance",
    "summary" : "",
    "text" : [ 
        {
            "type" : "image",
            "name": "andreu31-02-01"
        },
        {
            "type" : "paragraph",
            "content" : "Eròtic m'allibero, amb el darrer gemec dels difunts, l'erotisme de la seva essència despullada, preuada i condemnada a la terra de la joventut eterna. El dolor esdevé una flama dansant en un ball macabre."
        },
        {
            "type" : "paragraph",
            "content" : "Vestits en cerimoniosa comunió, aquells que m'han ignorat al llarg d'una vida, inclós jo mateix, han portat el meu cos fins a l'altar del darrer moment. Sota la fosforescència de les flames, l'últim acte físic neteja l'ànima. Tot s'esvaeix i en la ciutat em trobo amb tota l'abundància del meu passat, la bellesa dels que m'han aclamat ara cau com sorra de platja, esclatant en la primera alegria que neix des del fons de l'estómac."
        },
        {
            "type" : "paragraph",
            "content" : "<div style=\"display: flex; justify-content: center\"></br><div><i>Torno del somni amb un àngel trist.<div style=\"text-align: right\">(Carles Riba, Estances, II, 24)</div></i></div></br></div>"
        }
    ]
}