{
    "title" : "Ara el cel com una massa de terra sense ànima. Diari d’un nòmada sidós (15) Granada",
    "url" : "diari-d-un-nomada-sidos-15",
    "section" : "creacio",
    "issue" : 35,
    "data" : "31/05/2024",
    "imageCard" : "andreu35-01",
    "author" : "Andreu Pérez-Mingorance",
    "summary" : "",
    "text" : [ 
        {
            "type" : "image",
            "name": "andreu35-01"
        },
        {
            "type" : "paragraph",
            "content" : "La veu mullada d’aquell blau de tarda de setembre, d’aquell pes tan fort de llàgrimes de cel  que vessen sobre les espatlles. Passaran els dies i a qui plorar? A l’olor de terra humida i pa calent, tot just sortit del forn fumejant. No em quedaran súpliques ni de dies ni d’hores i no sabré com tornar a casa meva. El campanar marcarà hores al ritme dels meus peus amarats a les fonts que, com una sèquia, corrien per la meva boca i florien com roses als meus llavis, als meus genolls rosegats a l’última frontera de l’aigua. La boca dolça de l’últim pa amorosit de mantega i mel, mentre algú tanca la porta que mai més s’obrirà. L’animeta de la fornícula de dalt de l’escala ha quedat encesa, serà la meva ànima atrapada o lliure en el capvespre d’Exoche."
        },
        {
            "type" : "paragraph",
            "content" : "<div style=\"display: flex; justify-content: flex-end\"></br><div style=\"text-align: right;\"></br> <i> “No acierto a caminar. La noche se adhiere a mis huesos. Mis huesos. Mi pie vacila por la encrucijada de lo desconocido…” </i></br>(Juan Gutiérrez Padial, A Contratierra,  XXIV, p. 48 Ed. Veleta del Sur, Granada)</div></br></div>"
        }
    ]
}